uipath_mcp/__init__.py
uipath_mcp/middlewares.py
uipath_mcp/_cli/__init__.py
uipath_mcp/_cli/cli_init.py
uipath_mcp/_cli/cli_new.py
uipath_mcp/_cli/cli_run.py
uipath_mcp/_cli/_runtime/_context.py
uipath_mcp/_cli/_runtime/_exception.py
uipath_mcp/_cli/_runtime/_runtime.py
uipath_mcp/_cli/_runtime/_session.py
uipath_mcp/_cli/_runtime/_tracer.py
uipath_mcp/_cli/_templates/mcp.json.template
uipath_mcp/_cli/_templates/pyproject.toml.template
uipath_mcp/_cli/_templates/server.py.template
uipath_mcp/_cli/_utils/_config.py
uipath_mcp/_cli/_utils/_diagnose.py
uipath_mcp-0.0.106.dist-info/METADATA
uipath_mcp-0.0.106.dist-info/WHEEL
uipath_mcp-0.0.106.dist-info/entry_points.txt
uipath_mcp-0.0.106.dist-info/licenses/LICENSE
uipath_mcp-0.0.106.dist-info/RECORD
